marian_library/__init__.py
marian_library/gramer.py
marian_library/string_converter.py
marian_library/tests.py
marian_library/version.py
marian_library/data/dict.en.txt
marian_library/data/en-ptb_map
marian_library/data/en_GB-large.txt
marian_library/errant_tools/__init__.py
marian_library/errant_tools/align_text.py
marian_library/errant_tools/cat_rules.py
marian_library/errant_tools/rdlextra.py
marian_library/errant_tools/toolbox.py
marian_library-0.56.0.dist-info/METADATA
marian_library-0.56.0.dist-info/WHEEL
marian_library-0.56.0.dist-info/top_level.txt
marian_library-0.56.0.dist-info/RECORD
